e2b_mcp_server/__init__.py
e2b_mcp_server/server.py
e2b_mcp_server-0.1.1.dist-info/METADATA
e2b_mcp_server-0.1.1.dist-info/WHEEL
e2b_mcp_server-0.1.1.dist-info/RECORD
